README.md
setup.cfg
setup.py
qiskit_utils/__init__.py
qiskit_utils/enhanced_circuit.py
qiskit_utils/insert.py
qiskit_utils/parse_counts.py
qiskit_utils/parse_result.py
qiskit_utils.egg-info/PKG-INFO
qiskit_utils.egg-info/SOURCES.txt
qiskit_utils.egg-info/dependency_links.txt
qiskit_utils.egg-info/requires.txt
qiskit_utils.egg-info/top_level.txt