Metadata-Version: 2.1
Name: qiskit-utils
Version: 1.2.1
Summary: package containing utility methods for qiskit like result parsing and instruction insertion for circuits
Home-page: https://github.com/mgrzesiuk/qiskit-utils
Author: Marek Grzesiuk
License: MIT
Keywords: utility-methods qiskit
Platform: UNKNOWN
